lite_lib2/__init__.py
super_duper_lib/__init__.py
lite_lib2-0.1.1.dist-info/METADATA
lite_lib2-0.1.1.dist-info/WHEEL
lite_lib2-0.1.1.dist-info/top_level.txt
lite_lib2-0.1.1.dist-info/RECORD
