Metadata-Version: 2.1
Name: lite-lib2
Version: 0.1.1
Requires-Dist: pygame >=2.0.0
